EasyTweeter.py
EasyTweeter-0.10.1.dist-info/LICENSE
EasyTweeter-0.10.1.dist-info/METADATA
EasyTweeter-0.10.1.dist-info/WHEEL
EasyTweeter-0.10.1.dist-info/top_level.txt
EasyTweeter-0.10.1.dist-info/RECORD
